audiolm/__init__.py
audiolm-0.0.1.dev0.dist-info/METADATA
audiolm-0.0.1.dev0.dist-info/WHEEL
audiolm-0.0.1.dev0.dist-info/top_level.txt
audiolm-0.0.1.dev0.dist-info/RECORD
