Metadata-Version: 2.1
Name: audiolm
Version: 0.0.1.dev0
Summary: AudioLM - Language Modeling Approach to Audio Generation
Author: Shadow Walker
License: UNKNOWN
Keywords: audiolm
Platform: UNKNOWN
Classifier: Programming Language :: Python :: 3
Classifier: Programming Language :: Python :: 3.8
Classifier: Programming Language :: Python :: 3.9
Classifier: Programming Language :: Python :: 3.10
Requires-Dist: torch
